flake8_mock.py
flake8_mock-0.4.dist-info/LICENSE
flake8_mock-0.4.dist-info/METADATA
flake8_mock-0.4.dist-info/WHEEL
flake8_mock-0.4.dist-info/entry_points.txt
flake8_mock-0.4.dist-info/top_level.txt
flake8_mock-0.4.dist-info/RECORD
