Metadata-Version: 2.1
Name: flake8-mock
Version: 0.4
Summary: Provides checking for non-existent mock methods
Home-page: https://github.com/aleGpereira/flake8-mock
Author: Alejandro Pereira
Author-email: alepereira.dev@gmail.com
License: GNU
Keywords: flake8,mock,testing
Classifier: Development Status :: 3 - Alpha
Classifier: Environment :: Console
Classifier: Intended Audience :: Developers
Classifier: License :: OSI Approved :: GNU General Public License v2 (GPLv2)
Classifier: Operating System :: OS Independent
Classifier: Programming Language :: Python
Classifier: Programming Language :: Python :: 2
Classifier: Topic :: Software Development :: Libraries :: Python Modules
Classifier: Topic :: Software Development :: Quality Assurance
License-File: LICENSE
